canica/__init__.py
canica/data.py
canica/py.typed
canica/standalone_widget.py
canica/widget.py
canica/static/widget.css
canica/static/widget.js
canica-0.0.19.dist-info/METADATA
canica-0.0.19.dist-info/WHEEL
canica-0.0.19.dist-info/licenses/LICENSE
canica-0.0.19.dist-info/RECORD
