Metadata-Version: 2.1
Name: canica
Version: 0.0.19
License: MIT License
License-File: LICENSE
Requires-Python: >=3.9
Requires-Dist: anywidget>=0.6.5
Requires-Dist: importlib-metadata
Requires-Dist: jupyterlab>=4.0.6
Requires-Dist: numpy>=1.24
Requires-Dist: pandas>=2.0
Requires-Dist: pyarrow>=13.0.0
Requires-Dist: pydantic>=2.4.2
Requires-Dist: traitlets>=5.13.0
Provides-Extra: dev
Requires-Dist: black>=23.9.1; extra == 'dev'
Requires-Dist: canica[test]; extra == 'dev'
Requires-Dist: jupyterlab>=4.0.7; extra == 'dev'
Requires-Dist: mypy>=1.5.1; extra == 'dev'
Requires-Dist: nbstripout>=0.6.1; extra == 'dev'
Requires-Dist: pandas-stubs>=2.1.1.230928; extra == 'dev'
Requires-Dist: pre-commit>=3.4.0; extra == 'dev'
Requires-Dist: watchfiles>=0.20.0; extra == 'dev'
Provides-Extra: test
Requires-Dist: pytest>=7.4.2; extra == 'test'
